roamrs/__init__.py
roamrs/auth.py
roamrs/cog.py
roamrs/common.py
roamrs/context.py
roamrs/extensions.py
roamrs/flycheck_httpserver.py
roamrs/httpserver.py
roamrs/pyjwt.py
roamrs/services.py
roamrs-0.3.3.dist-info/LICENSE
roamrs-0.3.3.dist-info/METADATA
roamrs-0.3.3.dist-info/WHEEL
roamrs-0.3.3.dist-info/top_level.txt
roamrs-0.3.3.dist-info/RECORD
